{"_type":"export","__export_format":4,"__export_date":"2023-10-24T18:43:49.571Z","__export_source":"insomnia.desktop.app:v8.3.0","resources":[{"_id":"req_7a7b465aea1049e08801e38fcff3a7a3","parentId":"wrk_54b7e745fe3e424cb5939075e63edac6","modified":1698163309882,"created":1698163019076,"url":"{{url}}/log","name":"New Log","description":"","method":"POST","body":{"mimeType":"application/json","text":"{\n\t\"data\":{\n\t\t\"table\":\"teste\",\n\t\t\"sender_id\":\"xx\",\n\t\t\"metadata\":{},\n\t\t\"before\":{\n\t\t\t\"campo_1\":1\n\t\t},\n\t\t\"after\":{\n\t\t\t\"campo_1\":2\n\t\t}\n\t},\n\t\"system_id\":\"teste\",\n\t \"tags\":[\n\t\t \"teste\",\n\t\t \"x\",\n\t\t \"searchable\"\n\t ]\n}"},"parameters":[],"headers":[{"name":"Content-Type","value":"application/json"},{"name":"User-Agent","value":"insomnia/8.3.0"}],"authentication":{},"metaSortKey":-1698163019076,"isPrivate":false,"settingStoreCookies":true,"settingSendCookies":true,"settingDisableRenderRequestBody":false,"settingEncodeUrl":true,"settingRebuildPath":true,"settingFollowRedirects":"global","_type":"request"},{"_id":"wrk_54b7e745fe3e424cb5939075e63edac6","parentId":null,"modified":1698163015685,"created":1698163015686,"name":"[BlockChain] Logger","description":"","scope":"collection","_type":"workspace"},{"_id":"req_b02e6a79399349cca6cd4bc27fcef67e","parentId":"wrk_54b7e745fe3e424cb5939075e63edac6","modified":1698164222610,"created":1698164216175,"url":"{{url}}/validate","name":"validate","description":"","method":"GET","body":{},"parameters":[],"headers":[{"name":"User-Agent","value":"insomnia/8.3.0"}],"authentication":{},"metaSortKey":-1698130597489,"isPrivate":false,"settingStoreCookies":true,"settingSendCookies":true,"settingDisableRenderRequestBody":false,"settingEncodeUrl":true,"settingRebuildPath":true,"settingFollowRedirects":"global","_type":"request"},{"_id":"req_23a8022c8ed344dc939633f4b5c1362c","parentId":"wrk_54b7e745fe3e424cb5939075e63edac6","modified":1698172753828,"created":1698164680522,"url":"{{url}}/validate/22/220","name":"validate segment","description":"","method":"GET","body":{},"parameters":[],"headers":[{"name":"User-Agent","value":"insomnia/8.3.0"}],"authentication":{},"metaSortKey":-1698114386695.5,"isPrivate":false,"settingStoreCookies":true,"settingSendCookies":true,"settingDisableRenderRequestBody":false,"settingEncodeUrl":true,"settingRebuildPath":true,"settingFollowRedirects":"global","_type":"request"},{"_id":"env_0b6ff68840cb253a2f908dc1f555f25f590230d1","parentId":"wrk_54b7e745fe3e424cb5939075e63edac6","modified":1698163015690,"created":1698163015690,"name":"Base Environment","data":{},"dataPropertyOrder":null,"color":null,"isPrivate":false,"metaSortKey":1698163015690,"_type":"environment"},{"_id":"jar_0b6ff68840cb253a2f908dc1f555f25f590230d1","parentId":"wrk_54b7e745fe3e424cb5939075e63edac6","modified":1698163015693,"created":1698163015693,"name":"Default Jar","cookies":[],"_type":"cookie_jar"},{"_id":"env_93c1a927c51840a58bef3c45a8777b5b","parentId":"env_0b6ff68840cb253a2f908dc1f555f25f590230d1","modified":1698163056553,"created":1698163035270,"name":"local","data":{"url":"http://localhost:5656"},"dataPropertyOrder":{"&":["url"]},"color":null,"isPrivate":true,"metaSortKey":1698163035270,"_type":"environment"}]}